trimesh/__init__.py
trimesh/__main__.py
trimesh/base.py
trimesh/boolean.py
trimesh/bounds.py
trimesh/caching.py
trimesh/collision.py
trimesh/comparison.py
trimesh/constants.py
trimesh/convex.py
trimesh/creation.py
trimesh/curvature.py
trimesh/decomposition.py
trimesh/exceptions.py
trimesh/geometry.py
trimesh/graph.py
trimesh/grouping.py
trimesh/inertia.py
trimesh/intersections.py
trimesh/interval.py
trimesh/iteration.py
trimesh/nsphere.py
trimesh/parent.py
trimesh/permutate.py
trimesh/points.py
trimesh/poses.py
trimesh/primitives.py
trimesh/proximity.py
trimesh/py.typed
trimesh/registration.py
trimesh/remesh.py
trimesh/rendering.py
trimesh/repair.py
trimesh/resolvers.py
trimesh/sample.py
trimesh/schemas.py
trimesh/smoothing.py
trimesh/transformations.py
trimesh/triangles.py
trimesh/typed.py
trimesh/units.py
trimesh/util.py
trimesh/version.py
trimesh/exchange/__init__.py
trimesh/exchange/binvox.py
trimesh/exchange/cascade.py
trimesh/exchange/dae.py
trimesh/exchange/export.py
trimesh/exchange/gltf.py
trimesh/exchange/load.py
trimesh/exchange/misc.py
trimesh/exchange/obj.py
trimesh/exchange/off.py
trimesh/exchange/ply.py
trimesh/exchange/stl.py
trimesh/exchange/threedxml.py
trimesh/exchange/threemf.py
trimesh/exchange/urdf.py
trimesh/exchange/xaml.py
trimesh/exchange/xyz.py
trimesh/interfaces/__init__.py
trimesh/interfaces/blender.py
trimesh/interfaces/generic.py
trimesh/path/__init__.py
trimesh/path/arc.py
trimesh/path/creation.py
trimesh/path/curve.py
trimesh/path/entities.py
trimesh/path/intersections.py
trimesh/path/packing.py
trimesh/path/path.py
trimesh/path/polygons.py
trimesh/path/raster.py
trimesh/path/repair.py
trimesh/path/segments.py
trimesh/path/simplify.py
trimesh/path/traversal.py
trimesh/path/util.py
trimesh/path/exchange/__init__.py
trimesh/path/exchange/dxf.py
trimesh/path/exchange/export.py
trimesh/path/exchange/load.py
trimesh/path/exchange/misc.py
trimesh/path/exchange/svg_io.py
trimesh/ray/__init__.py
trimesh/ray/ray_pyembree.py
trimesh-4.8.0.dist-info/licenses/LICENSE.md
trimesh-4.8.0.dist-info/METADATA
trimesh-4.8.0.dist-info/WHEEL
trimesh-4.8.0.dist-info/entry_points.txt
trimesh-4.8.0.dist-info/top_level.txt
trimesh-4.8.0.dist-info/RECORD
